{
    "ret": 13,
    "data": [
        {
            "name": "RTX 3090",
            "price": 15999,
            "pic": "/3090.jpg"
        },
        {
            "name": "RTX 3090",
            "price": 15999,
            "pic": "/3090.jpg"
        },
        {
            "name": "RTX 3090",
            "price": 15999,
            "pic": "/3090.jpg"
        },
        {
            "name": "RTX 3090",
            "price": 15999,
            "pic": "/3090.jpg"
        },
        {
            "name": "RTX 3090",
            "price": 15999,
            "pic": "/3090.jpg"
        },
        {
            "name": "RTX 3090",
            "price": 15999,
            "pic": "/3090.jpg"
        },
        {
            "name": "RTX 3090",
            "price": 15999,
            "pic": "/3090.jpg"
        },
        {
            "name": "RTX 3090",
            "price": 15999,
            "pic": "/3090.jpg"
        },
        {
            "name": "RTX 3090",
            "price": 15999,
            "pic": "/3090.jpg"
        },
        {
            "name": "RTX 3090",
            "price": 15999,
            "pic": "/3090.jpg"
        },
        {
            "name": "RTX 3090",
            "price": 15999,
            "pic": "/3090.jpg"
        },
        {
            "name": "RTX 3090",
            "price": 15999,
            "pic": "/3090.jpg"
        },
        {
            "name": "RTX 3090",
            "price": 15999,
            "pic": "/3090.jpg"
        }
    ]
}